setup.py
graphicsmagick_engine/__init__.py
graphicsmagick_engine/engine.py
graphicsmagick_engine.egg-info/PKG-INFO
graphicsmagick_engine.egg-info/SOURCES.txt
graphicsmagick_engine.egg-info/dependency_links.txt
graphicsmagick_engine.egg-info/requires.txt
graphicsmagick_engine.egg-info/top_level.txt
tests/__init__.py
tests/integration/__init__.py
tests/integration/graphicsmagick_test.py
tests/unit/__init__.py