Metadata-Version: 1.1
Name: graphicsmagick-engine
Version: 0.1.1
Summary: GraphicsMagick imaging engine for thumbor.
Home-page: UNKNOWN
Author: Globo.com
Author-email: timehome@corp.globo.com
License: MIT
Keywords: thumbor imaging graphicsmagick
Platform: UNKNOWN
Classifier: Development Status :: 4 - Beta
Classifier: Intended Audience :: Developers
Classifier: License :: OSI Approved :: MIT License
Classifier: Natural Language :: English
Classifier: Operating System :: MacOS
Classifier: Operating System :: POSIX
Classifier: Operating System :: Unix
Classifier: Operating System :: OS Independent
Classifier: Programming Language :: Python :: 2.7
